README.rst
setup.py
kwconfig/__init__.py
kwconfig.egg-info/PKG-INFO
kwconfig.egg-info/SOURCES.txt
kwconfig.egg-info/dependency_links.txt
kwconfig.egg-info/top_level.txt