Metadata-Version: 1.1
Name: kwconfig
Version: 1.1.0
Summary: A Python module for managing config files in keyword style json format.
Home-page: https://github.com/rrwen/kwconfig
Author: Richard Wen
Author-email: rrwen.dev@gmail.com
License: MIT
Download-URL: https://github.com/rrwen/kwconfig/archive/master.zip
Keywords: manage,config,keyword,key,word,value,keyvalue,json,file,path,module
Platform: UNKNOWN
